gfm_toc/__init__.py
gfm_toc/md_toc.py
gfm_toc-0.0.7.data/scripts/gfm-toc
gfm_toc-0.0.7.dist-info/LICENSE
gfm_toc-0.0.7.dist-info/METADATA
gfm_toc-0.0.7.dist-info/WHEEL
gfm_toc-0.0.7.dist-info/top_level.txt
gfm_toc-0.0.7.dist-info/RECORD
