Metadata-Version: 2.1
Name: gfm-toc
Version: 0.0.7
Summary: Simple and customizable way to generate TOC for Github Markdown files.
Home-page: https://github.com/waynerv/github-markdown-toc
Author: Xie Wei
Author-email: ampedee@gmail.com
License: MIT
Keywords: markdown md github gfm table of contents toc
Platform: Linux & OSX
Classifier: Development Status :: 4 - Beta
Classifier: Environment :: Console
Classifier: Intended Audience :: Developers
Classifier: License :: OSI Approved :: MIT License
Classifier: Programming Language :: Python
Classifier: Programming Language :: Python :: 3
Classifier: Programming Language :: Python :: 3.3
Classifier: Programming Language :: Python :: 3.4
Classifier: Programming Language :: Python :: 3.5
Classifier: Programming Language :: Python :: 3.6
Classifier: Topic :: Terminals
Classifier: Topic :: Text Editors :: Text Processing
Classifier: Topic :: Text Processing
Classifier: Operating System :: POSIX :: Linux
Classifier: Operating System :: MacOS
